{"total":1,"pageSize":13,"pageCount":1,"data":[{"title":"Hello World","uid":"b9663f58f18133b35bfe243f3e916a80","slug":"hello-world","date":"2021-08-25T06:28:50.572Z","updated":"2021-08-25T06:28:50.572Z","comments":true,"path":"api/articles/hello-world.json","cover":null,"text":"Welcome to Hexo! This is your very first post. Check documentation for more info. If you get any problems when using Hexo, you can find the ...","link":"","photos":[],"count_time":{"symbolsCount":430,"symbolsTime":"1 mins."},"categories":[],"tags":[],"author":{"name":"tutu","slug":"blog-author","avatar":"https://s3.bmp.ovh/imgs/2021/08/21c5941d7bc1f8fa.png","link":"/","description":"","socials":{"github":"","twitter":"","stackoverflow":"","wechat":"","qq":"","weibo":"","zhihu":"","csdn":"","juejin":"","customs":{}}}}]}